[{"id":107,"date":"2026-02-06T03:40:42","date_gmt":"2026-02-06T03:40:42","guid":{"rendered":"https:\/\/pakhams.com\/wp-content\/uploads\/2026\/02\/SWL-Membership-Form-2026.pdf"},"modified":"2026-02-06T03:40:42","modified_gmt":"2026-02-06T03:40:42","slug":"swl-membership-form-2026","status":"inherit","type":"attachment","link":"https:\/\/pakhams.com\/swl-membership-form-2026\/","title":{"rendered":"SWL Membership Form &#8211; 2026"},"author":1,"featured_media":0,"comment_status":"","ping_status":"closed","template":"","meta":{"pagelayer_contact_templates":[],"_pagelayer_content":""},"class_list":["post-107","attachment","type-attachment","status-inherit","hentry"],"description":{"rendered":"<p class=\"attachment\"><a href='https:\/\/pakhams.com\/wp-content\/uploads\/2026\/02\/SWL-Membership-Form-2026.pdf'>SWL Membership Form - 2026<\/a><\/p>\n"},"caption":{"rendered":"<p>SWL Membership Form &#8211; 2026<\/p>\n"},"alt_text":"","media_type":"file","mime_type":"application\/pdf","media_details":{"filesize":110041,"sizes":{}},"post":null,"source_url":"https:\/\/pakhams.com\/wp-content\/uploads\/2026\/02\/SWL-Membership-Form-2026.pdf","_links":{"self":[{"href":"https:\/\/pakhams.com\/wp-json\/wp\/v2\/media\/107","targetHints":{"allow":["GET"]}}],"collection":[{"href":"https:\/\/pakhams.com\/wp-json\/wp\/v2\/media"}],"about":[{"href":"https:\/\/pakhams.com\/wp-json\/wp\/v2\/types\/attachment"}],"author":[{"embeddable":true,"href":"https:\/\/pakhams.com\/wp-json\/wp\/v2\/users\/1"}],"replies":[{"embeddable":true,"href":"https:\/\/pakhams.com\/wp-json\/wp\/v2\/comments?post=107"}]}},{"id":82,"date":"2024-11-05T07:05:20","date_gmt":"2024-11-05T07:05:20","guid":{"rendered":"https:\/\/pakhams.com\/wp-content\/uploads\/2024\/11\/SWL-Form-V1-2024-.pdf"},"modified":"2024-11-05T07:05:20","modified_gmt":"2024-11-05T07:05:20","slug":"swl-form-v1-2024","status":"inherit","type":"attachment","link":"https:\/\/pakhams.com\/swl-form-v1-2024\/","title":{"rendered":"SWL Form V1 2024"},"author":1,"featured_media":0,"comment_status":"","ping_status":"closed","template":"","meta":{"pagelayer_contact_templates":[],"_pagelayer_content":""},"class_list":["post-82","attachment","type-attachment","status-inherit","hentry"],"description":{"rendered":"<p class=\"attachment\"><a href='https:\/\/pakhams.com\/wp-content\/uploads\/2024\/11\/SWL-Form-V1-2024-.pdf'><img loading=\"lazy\" decoding=\"async\" width=\"212\" height=\"300\" src=\"https:\/\/pakhams.com\/wp-content\/uploads\/2024\/11\/SWL-Form-V1-2024-pdf-212x300.jpg\" class=\"attachment-medium size-medium\" alt=\"\" \/><\/a><\/p>\n"},"caption":{"rendered":""},"alt_text":"","media_type":"file","mime_type":"application\/pdf","media_details":{"sizes":{"full":{"file":"SWL-Form-V1-2024-pdf.jpg","width":1058,"height":1497,"mime_type":"application\/pdf","source_url":"https:\/\/pakhams.com\/wp-content\/uploads\/2024\/11\/SWL-Form-V1-2024-pdf.jpg"},"medium":{"file":"SWL-Form-V1-2024-pdf-212x300.jpg","width":212,"height":300,"filesize":13619,"mime_type":"image\/jpeg","source_url":"https:\/\/pakhams.com\/wp-content\/uploads\/2024\/11\/SWL-Form-V1-2024-pdf-212x300.jpg"},"large":{"file":"SWL-Form-V1-2024-pdf-724x1024.jpg","width":724,"height":1024,"filesize":82818,"mime_type":"image\/jpeg","source_url":"https:\/\/pakhams.com\/wp-content\/uploads\/2024\/11\/SWL-Form-V1-2024-pdf-724x1024.jpg"},"thumbnail":{"file":"SWL-Form-V1-2024-pdf-106x150.jpg","width":106,"height":150,"filesize":6578,"mime_type":"image\/jpeg","source_url":"https:\/\/pakhams.com\/wp-content\/uploads\/2024\/11\/SWL-Form-V1-2024-pdf-106x150.jpg"}},"filesize":169291},"post":null,"source_url":"https:\/\/pakhams.com\/wp-content\/uploads\/2024\/11\/SWL-Form-V1-2024-.pdf","_links":{"self":[{"href":"https:\/\/pakhams.com\/wp-json\/wp\/v2\/media\/82","targetHints":{"allow":["GET"]}}],"collection":[{"href":"https:\/\/pakhams.com\/wp-json\/wp\/v2\/media"}],"about":[{"href":"https:\/\/pakhams.com\/wp-json\/wp\/v2\/types\/attachment"}],"author":[{"embeddable":true,"href":"https:\/\/pakhams.com\/wp-json\/wp\/v2\/users\/1"}],"replies":[{"embeddable":true,"href":"https:\/\/pakhams.com\/wp-json\/wp\/v2\/comments?post=82"}]}},{"id":76,"date":"2024-11-05T06:23:55","date_gmt":"2024-11-05T06:23:55","guid":{"rendered":"https:\/\/pakhams.com\/wp-content\/uploads\/2024\/11\/440813909_881420720665615_3010760136099939531_n.jpg"},"modified":"2024-11-05T06:23:55","modified_gmt":"2024-11-05T06:23:55","slug":"440813909_881420720665615_3010760136099939531_n","status":"inherit","type":"attachment","link":"https:\/\/pakhams.com\/440813909_881420720665615_3010760136099939531_n\/","title":{"rendered":"440813909_881420720665615_3010760136099939531_n"},"author":1,"featured_media":0,"comment_status":"","ping_status":"closed","template":"","meta":{"pagelayer_contact_templates":[],"_pagelayer_content":""},"class_list":["post-76","attachment","type-attachment","status-inherit","hentry"],"description":{"rendered":"<p class=\"attachment\"><a href='https:\/\/pakhams.com\/wp-content\/uploads\/2024\/11\/440813909_881420720665615_3010760136099939531_n.jpg'><img loading=\"lazy\" decoding=\"async\" width=\"120\" height=\"300\" src=\"https:\/\/pakhams.com\/wp-content\/uploads\/2024\/11\/440813909_881420720665615_3010760136099939531_n-120x300.jpg\" class=\"attachment-medium size-medium\" alt=\"\" srcset=\"https:\/\/pakhams.com\/wp-content\/uploads\/2024\/11\/440813909_881420720665615_3010760136099939531_n-120x300.jpg 120w, https:\/\/pakhams.com\/wp-content\/uploads\/2024\/11\/440813909_881420720665615_3010760136099939531_n-410x1024.jpg 410w, https:\/\/pakhams.com\/wp-content\/uploads\/2024\/11\/440813909_881420720665615_3010760136099939531_n.jpg 600w\" sizes=\"auto, (max-width: 120px) 100vw, 120px\" \/><\/a><\/p>\n"},"caption":{"rendered":""},"alt_text":"","media_type":"image","mime_type":"image\/jpeg","media_details":{"width":600,"height":1500,"file":"2024\/11\/440813909_881420720665615_3010760136099939531_n.jpg","filesize":70059,"sizes":{"medium":{"file":"440813909_881420720665615_3010760136099939531_n-120x300.jpg","width":120,"height":300,"filesize":9413,"mime_type":"image\/jpeg","source_url":"https:\/\/pakhams.com\/wp-content\/uploads\/2024\/11\/440813909_881420720665615_3010760136099939531_n-120x300.jpg"},"large":{"file":"440813909_881420720665615_3010760136099939531_n-410x1024.jpg","width":410,"height":1024,"filesize":50416,"mime_type":"image\/jpeg","source_url":"https:\/\/pakhams.com\/wp-content\/uploads\/2024\/11\/440813909_881420720665615_3010760136099939531_n-410x1024.jpg"},"thumbnail":{"file":"440813909_881420720665615_3010760136099939531_n-150x150.jpg","width":150,"height":150,"filesize":6273,"mime_type":"image\/jpeg","source_url":"https:\/\/pakhams.com\/wp-content\/uploads\/2024\/11\/440813909_881420720665615_3010760136099939531_n-150x150.jpg"},"full":{"file":"440813909_881420720665615_3010760136099939531_n.jpg","width":600,"height":1500,"mime_type":"image\/jpeg","source_url":"https:\/\/pakhams.com\/wp-content\/uploads\/2024\/11\/440813909_881420720665615_3010760136099939531_n.jpg"}},"image_meta":{"aperture":"0","credit":"","camera":"","caption":"","created_timestamp":"0","copyright":"","focal_length":"0","iso":"0","shutter_speed":"0","title":"","orientation":"0","keywords":[]}},"post":null,"source_url":"https:\/\/pakhams.com\/wp-content\/uploads\/2024\/11\/440813909_881420720665615_3010760136099939531_n.jpg","_links":{"self":[{"href":"https:\/\/pakhams.com\/wp-json\/wp\/v2\/media\/76","targetHints":{"allow":["GET"]}}],"collection":[{"href":"https:\/\/pakhams.com\/wp-json\/wp\/v2\/media"}],"about":[{"href":"https:\/\/pakhams.com\/wp-json\/wp\/v2\/types\/attachment"}],"author":[{"embeddable":true,"href":"https:\/\/pakhams.com\/wp-json\/wp\/v2\/users\/1"}],"replies":[{"embeddable":true,"href":"https:\/\/pakhams.com\/wp-json\/wp\/v2\/comments?post=76"}]}},{"id":56,"date":"2024-11-03T14:20:30","date_gmt":"2024-11-03T14:20:30","guid":{"rendered":"https:\/\/pakhams.com\/wp-content\/uploads\/2024\/11\/IMG-20140109-WA001_2-removebg-preview.png"},"modified":"2024-11-03T14:20:30","modified_gmt":"2024-11-03T14:20:30","slug":"img-20140109-wa001_2-removebg-preview","status":"inherit","type":"attachment","link":"https:\/\/pakhams.com\/?attachment_id=56","title":{"rendered":"IMG-20140109-WA001_2-removebg-preview"},"author":1,"featured_media":0,"comment_status":"open","ping_status":"closed","template":"","meta":{"pagelayer_contact_templates":[],"_pagelayer_content":""},"class_list":["post-56","attachment","type-attachment","status-inherit","hentry"],"description":{"rendered":"<p class=\"attachment\"><a href='https:\/\/pakhams.com\/wp-content\/uploads\/2024\/11\/IMG-20140109-WA001_2-removebg-preview.png'><img loading=\"lazy\" decoding=\"async\" width=\"300\" height=\"300\" src=\"https:\/\/pakhams.com\/wp-content\/uploads\/2024\/11\/IMG-20140109-WA001_2-removebg-preview-300x300.png\" class=\"attachment-medium size-medium\" alt=\"\" srcset=\"https:\/\/pakhams.com\/wp-content\/uploads\/2024\/11\/IMG-20140109-WA001_2-removebg-preview-300x300.png 300w, https:\/\/pakhams.com\/wp-content\/uploads\/2024\/11\/IMG-20140109-WA001_2-removebg-preview-150x150.png 150w, https:\/\/pakhams.com\/wp-content\/uploads\/2024\/11\/IMG-20140109-WA001_2-removebg-preview.png 500w\" sizes=\"auto, (max-width: 300px) 100vw, 300px\" \/><\/a><\/p>\n"},"caption":{"rendered":""},"alt_text":"","media_type":"image","mime_type":"image\/png","media_details":{"width":500,"height":500,"file":"2024\/11\/IMG-20140109-WA001_2-removebg-preview.png","filesize":257919,"sizes":{"medium":{"file":"IMG-20140109-WA001_2-removebg-preview-300x300.png","width":300,"height":300,"filesize":105919,"mime_type":"image\/png","source_url":"https:\/\/pakhams.com\/wp-content\/uploads\/2024\/11\/IMG-20140109-WA001_2-removebg-preview-300x300.png"},"thumbnail":{"file":"IMG-20140109-WA001_2-removebg-preview-150x150.png","width":150,"height":150,"filesize":34963,"mime_type":"image\/png","source_url":"https:\/\/pakhams.com\/wp-content\/uploads\/2024\/11\/IMG-20140109-WA001_2-removebg-preview-150x150.png"},"full":{"file":"IMG-20140109-WA001_2-removebg-preview.png","width":500,"height":500,"mime_type":"image\/png","source_url":"https:\/\/pakhams.com\/wp-content\/uploads\/2024\/11\/IMG-20140109-WA001_2-removebg-preview.png"}},"image_meta":{"aperture":"0","credit":"","camera":"","caption":"","created_timestamp":"0","copyright":"","focal_length":"0","iso":"0","shutter_speed":"0","title":"","orientation":"0","keywords":[]}},"post":8,"source_url":"https:\/\/pakhams.com\/wp-content\/uploads\/2024\/11\/IMG-20140109-WA001_2-removebg-preview.png","_links":{"self":[{"href":"https:\/\/pakhams.com\/wp-json\/wp\/v2\/media\/56","targetHints":{"allow":["GET"]}}],"collection":[{"href":"https:\/\/pakhams.com\/wp-json\/wp\/v2\/media"}],"about":[{"href":"https:\/\/pakhams.com\/wp-json\/wp\/v2\/types\/attachment"}],"author":[{"embeddable":true,"href":"https:\/\/pakhams.com\/wp-json\/wp\/v2\/users\/1"}],"replies":[{"embeddable":true,"href":"https:\/\/pakhams.com\/wp-json\/wp\/v2\/comments?post=56"}],"wp:attached-to":[{"embeddable":true,"post_type":"wp_template","id":8,"href":"https:\/\/pakhams.com\/wp-json\/wp\/v2\/templates\/8"}],"curies":[{"name":"wp","href":"https:\/\/api.w.org\/{rel}","templated":true}]}},{"id":49,"date":"2024-11-03T14:08:56","date_gmt":"2024-11-03T14:08:56","guid":{"rendered":"https:\/\/pakhams.com\/wp-content\/uploads\/2024\/11\/IMG-20140109-WA001_2.png"},"modified":"2024-11-03T14:08:56","modified_gmt":"2024-11-03T14:08:56","slug":"img-20140109-wa001_2","status":"inherit","type":"attachment","link":"https:\/\/pakhams.com\/?attachment_id=49","title":{"rendered":"IMG-20140109-WA001_2"},"author":1,"featured_media":0,"comment_status":"open","ping_status":"closed","template":"","meta":{"pagelayer_contact_templates":[],"_pagelayer_content":""},"class_list":["post-49","attachment","type-attachment","status-inherit","hentry"],"description":{"rendered":"<p class=\"attachment\"><a href='https:\/\/pakhams.com\/wp-content\/uploads\/2024\/11\/IMG-20140109-WA001_2.png'><img loading=\"lazy\" decoding=\"async\" width=\"300\" height=\"300\" src=\"https:\/\/pakhams.com\/wp-content\/uploads\/2024\/11\/IMG-20140109-WA001_2-300x300.png\" class=\"attachment-medium size-medium\" alt=\"\" srcset=\"https:\/\/pakhams.com\/wp-content\/uploads\/2024\/11\/IMG-20140109-WA001_2-300x300.png 300w, https:\/\/pakhams.com\/wp-content\/uploads\/2024\/11\/IMG-20140109-WA001_2-150x150.png 150w, https:\/\/pakhams.com\/wp-content\/uploads\/2024\/11\/IMG-20140109-WA001_2.png 640w\" sizes=\"auto, (max-width: 300px) 100vw, 300px\" \/><\/a><\/p>\n"},"caption":{"rendered":""},"alt_text":"","media_type":"image","mime_type":"image\/png","media_details":{"width":640,"height":640,"file":"2024\/11\/IMG-20140109-WA001_2.png","filesize":396165,"sizes":{"medium":{"file":"IMG-20140109-WA001_2-300x300.png","width":300,"height":300,"filesize":109142,"mime_type":"image\/png","source_url":"https:\/\/pakhams.com\/wp-content\/uploads\/2024\/11\/IMG-20140109-WA001_2-300x300.png"},"thumbnail":{"file":"IMG-20140109-WA001_2-150x150.png","width":150,"height":150,"filesize":33958,"mime_type":"image\/png","source_url":"https:\/\/pakhams.com\/wp-content\/uploads\/2024\/11\/IMG-20140109-WA001_2-150x150.png"},"full":{"file":"IMG-20140109-WA001_2.png","width":640,"height":640,"mime_type":"image\/png","source_url":"https:\/\/pakhams.com\/wp-content\/uploads\/2024\/11\/IMG-20140109-WA001_2.png"}},"image_meta":{"aperture":"0","credit":"","camera":"","caption":"","created_timestamp":"0","copyright":"","focal_length":"0","iso":"0","shutter_speed":"0","title":"","orientation":"0","keywords":[]}},"post":8,"source_url":"https:\/\/pakhams.com\/wp-content\/uploads\/2024\/11\/IMG-20140109-WA001_2.png","_links":{"self":[{"href":"https:\/\/pakhams.com\/wp-json\/wp\/v2\/media\/49","targetHints":{"allow":["GET"]}}],"collection":[{"href":"https:\/\/pakhams.com\/wp-json\/wp\/v2\/media"}],"about":[{"href":"https:\/\/pakhams.com\/wp-json\/wp\/v2\/types\/attachment"}],"author":[{"embeddable":true,"href":"https:\/\/pakhams.com\/wp-json\/wp\/v2\/users\/1"}],"replies":[{"embeddable":true,"href":"https:\/\/pakhams.com\/wp-json\/wp\/v2\/comments?post=49"}],"wp:attached-to":[{"embeddable":true,"post_type":"wp_template","id":8,"href":"https:\/\/pakhams.com\/wp-json\/wp\/v2\/templates\/8"}],"curies":[{"name":"wp","href":"https:\/\/api.w.org\/{rel}","templated":true}]}},{"id":47,"date":"2024-11-03T14:06:32","date_gmt":"2024-11-03T14:06:32","guid":{"rendered":"https:\/\/pakhams.com\/wp-content\/uploads\/2024\/11\/1472384.jpg"},"modified":"2024-11-03T14:06:32","modified_gmt":"2024-11-03T14:06:32","slug":"1472384","status":"inherit","type":"attachment","link":"https:\/\/pakhams.com\/?attachment_id=47","title":{"rendered":"1472384"},"author":1,"featured_media":0,"comment_status":"open","ping_status":"closed","template":"","meta":{"pagelayer_contact_templates":[],"_pagelayer_content":""},"class_list":["post-47","attachment","type-attachment","status-inherit","hentry"],"description":{"rendered":"<p class=\"attachment\"><a href='https:\/\/pakhams.com\/wp-content\/uploads\/2024\/11\/1472384.jpg'><img loading=\"lazy\" decoding=\"async\" width=\"300\" height=\"188\" src=\"https:\/\/pakhams.com\/wp-content\/uploads\/2024\/11\/1472384-300x188.jpg\" class=\"attachment-medium size-medium\" alt=\"\" srcset=\"https:\/\/pakhams.com\/wp-content\/uploads\/2024\/11\/1472384-300x188.jpg 300w, https:\/\/pakhams.com\/wp-content\/uploads\/2024\/11\/1472384-1024x640.jpg 1024w, https:\/\/pakhams.com\/wp-content\/uploads\/2024\/11\/1472384-768x480.jpg 768w, https:\/\/pakhams.com\/wp-content\/uploads\/2024\/11\/1472384-1536x960.jpg 1536w, https:\/\/pakhams.com\/wp-content\/uploads\/2024\/11\/1472384.jpg 1920w\" sizes=\"auto, (max-width: 300px) 100vw, 300px\" \/><\/a><\/p>\n"},"caption":{"rendered":""},"alt_text":"","media_type":"image","mime_type":"image\/jpeg","media_details":{"width":1920,"height":1200,"file":"2024\/11\/1472384.jpg","filesize":563816,"sizes":{"medium":{"file":"1472384-300x188.jpg","width":300,"height":188,"filesize":11576,"mime_type":"image\/jpeg","source_url":"https:\/\/pakhams.com\/wp-content\/uploads\/2024\/11\/1472384-300x188.jpg"},"large":{"file":"1472384-1024x640.jpg","width":1024,"height":640,"filesize":101452,"mime_type":"image\/jpeg","source_url":"https:\/\/pakhams.com\/wp-content\/uploads\/2024\/11\/1472384-1024x640.jpg"},"thumbnail":{"file":"1472384-150x150.jpg","width":150,"height":150,"filesize":6301,"mime_type":"image\/jpeg","source_url":"https:\/\/pakhams.com\/wp-content\/uploads\/2024\/11\/1472384-150x150.jpg"},"medium_large":{"file":"1472384-768x480.jpg","width":768,"height":480,"filesize":62940,"mime_type":"image\/jpeg","source_url":"https:\/\/pakhams.com\/wp-content\/uploads\/2024\/11\/1472384-768x480.jpg"},"1536x1536":{"file":"1472384-1536x960.jpg","width":1536,"height":960,"filesize":194869,"mime_type":"image\/jpeg","source_url":"https:\/\/pakhams.com\/wp-content\/uploads\/2024\/11\/1472384-1536x960.jpg"},"full":{"file":"1472384.jpg","width":1920,"height":1200,"mime_type":"image\/jpeg","source_url":"https:\/\/pakhams.com\/wp-content\/uploads\/2024\/11\/1472384.jpg"}},"image_meta":{"aperture":"0","credit":"","camera":"","caption":"","created_timestamp":"0","copyright":"","focal_length":"0","iso":"0","shutter_speed":"0","title":"","orientation":"0","keywords":[]}},"post":8,"source_url":"https:\/\/pakhams.com\/wp-content\/uploads\/2024\/11\/1472384.jpg","_links":{"self":[{"href":"https:\/\/pakhams.com\/wp-json\/wp\/v2\/media\/47","targetHints":{"allow":["GET"]}}],"collection":[{"href":"https:\/\/pakhams.com\/wp-json\/wp\/v2\/media"}],"about":[{"href":"https:\/\/pakhams.com\/wp-json\/wp\/v2\/types\/attachment"}],"author":[{"embeddable":true,"href":"https:\/\/pakhams.com\/wp-json\/wp\/v2\/users\/1"}],"replies":[{"embeddable":true,"href":"https:\/\/pakhams.com\/wp-json\/wp\/v2\/comments?post=47"}],"wp:attached-to":[{"embeddable":true,"post_type":"wp_template","id":8,"href":"https:\/\/pakhams.com\/wp-json\/wp\/v2\/templates\/8"}],"curies":[{"name":"wp","href":"https:\/\/api.w.org\/{rel}","templated":true}]}},{"id":37,"date":"2024-11-03T13:50:10","date_gmt":"2024-11-03T13:50:10","guid":{"rendered":"https:\/\/pakhams.com\/wp-content\/uploads\/2024\/11\/2.png"},"modified":"2024-11-03T13:50:10","modified_gmt":"2024-11-03T13:50:10","slug":"2","status":"inherit","type":"attachment","link":"https:\/\/pakhams.com\/become-member\/attachment\/2\/","title":{"rendered":"2"},"author":1,"featured_media":0,"comment_status":"open","ping_status":"closed","template":"","meta":{"pagelayer_contact_templates":[],"_pagelayer_content":""},"class_list":["post-37","attachment","type-attachment","status-inherit","hentry"],"description":{"rendered":"<p class=\"attachment\"><a href='https:\/\/pakhams.com\/wp-content\/uploads\/2024\/11\/2.png'><img loading=\"lazy\" decoding=\"async\" width=\"300\" height=\"162\" src=\"https:\/\/pakhams.com\/wp-content\/uploads\/2024\/11\/2-300x162.png\" class=\"attachment-medium size-medium\" alt=\"\" srcset=\"https:\/\/pakhams.com\/wp-content\/uploads\/2024\/11\/2-300x162.png 300w, https:\/\/pakhams.com\/wp-content\/uploads\/2024\/11\/2.png 501w\" sizes=\"auto, (max-width: 300px) 100vw, 300px\" \/><\/a><\/p>\n"},"caption":{"rendered":""},"alt_text":"","media_type":"image","mime_type":"image\/png","media_details":{"width":501,"height":270,"file":"2024\/11\/2.png","filesize":159659,"sizes":{"medium":{"file":"2-300x162.png","width":300,"height":162,"filesize":71119,"mime_type":"image\/png","source_url":"https:\/\/pakhams.com\/wp-content\/uploads\/2024\/11\/2-300x162.png"},"thumbnail":{"file":"2-150x150.png","width":150,"height":150,"filesize":41289,"mime_type":"image\/png","source_url":"https:\/\/pakhams.com\/wp-content\/uploads\/2024\/11\/2-150x150.png"},"full":{"file":"2.png","width":501,"height":270,"mime_type":"image\/png","source_url":"https:\/\/pakhams.com\/wp-content\/uploads\/2024\/11\/2.png"}},"image_meta":{"aperture":"0","credit":"","camera":"","caption":"","created_timestamp":"0","copyright":"","focal_length":"0","iso":"0","shutter_speed":"0","title":"","orientation":"0","keywords":[]}},"post":35,"source_url":"https:\/\/pakhams.com\/wp-content\/uploads\/2024\/11\/2.png","_links":{"self":[{"href":"https:\/\/pakhams.com\/wp-json\/wp\/v2\/media\/37","targetHints":{"allow":["GET"]}}],"collection":[{"href":"https:\/\/pakhams.com\/wp-json\/wp\/v2\/media"}],"about":[{"href":"https:\/\/pakhams.com\/wp-json\/wp\/v2\/types\/attachment"}],"author":[{"embeddable":true,"href":"https:\/\/pakhams.com\/wp-json\/wp\/v2\/users\/1"}],"replies":[{"embeddable":true,"href":"https:\/\/pakhams.com\/wp-json\/wp\/v2\/comments?post=37"}],"wp:attached-to":[{"embeddable":true,"post_type":"page","id":35,"href":"https:\/\/pakhams.com\/wp-json\/wp\/v2\/pages\/35"}],"curies":[{"name":"wp","href":"https:\/\/api.w.org\/{rel}","templated":true}]}},{"id":36,"date":"2024-11-03T13:49:35","date_gmt":"2024-11-03T13:49:35","guid":{"rendered":"https:\/\/pakhams.com\/wp-content\/uploads\/2024\/11\/1.png"},"modified":"2024-11-03T13:49:35","modified_gmt":"2024-11-03T13:49:35","slug":"1","status":"inherit","type":"attachment","link":"https:\/\/pakhams.com\/become-member\/attachment\/1\/","title":{"rendered":"1"},"author":1,"featured_media":0,"comment_status":"open","ping_status":"closed","template":"","meta":{"pagelayer_contact_templates":[],"_pagelayer_content":""},"class_list":["post-36","attachment","type-attachment","status-inherit","hentry"],"description":{"rendered":"<p class=\"attachment\"><a href='https:\/\/pakhams.com\/wp-content\/uploads\/2024\/11\/1.png'><img loading=\"lazy\" decoding=\"async\" width=\"300\" height=\"269\" src=\"https:\/\/pakhams.com\/wp-content\/uploads\/2024\/11\/1-300x269.png\" class=\"attachment-medium size-medium\" alt=\"\" srcset=\"https:\/\/pakhams.com\/wp-content\/uploads\/2024\/11\/1-300x269.png 300w, https:\/\/pakhams.com\/wp-content\/uploads\/2024\/11\/1.png 644w\" sizes=\"auto, (max-width: 300px) 100vw, 300px\" \/><\/a><\/p>\n"},"caption":{"rendered":""},"alt_text":"","media_type":"image","mime_type":"image\/png","media_details":{"width":644,"height":578,"file":"2024\/11\/1.png","filesize":160618,"sizes":{"medium":{"file":"1-300x269.png","width":300,"height":269,"filesize":61115,"mime_type":"image\/png","source_url":"https:\/\/pakhams.com\/wp-content\/uploads\/2024\/11\/1-300x269.png"},"thumbnail":{"file":"1-150x150.png","width":150,"height":150,"filesize":20375,"mime_type":"image\/png","source_url":"https:\/\/pakhams.com\/wp-content\/uploads\/2024\/11\/1-150x150.png"},"full":{"file":"1.png","width":644,"height":578,"mime_type":"image\/png","source_url":"https:\/\/pakhams.com\/wp-content\/uploads\/2024\/11\/1.png"}},"image_meta":{"aperture":"0","credit":"","camera":"","caption":"","created_timestamp":"0","copyright":"","focal_length":"0","iso":"0","shutter_speed":"0","title":"","orientation":"0","keywords":[]}},"post":35,"source_url":"https:\/\/pakhams.com\/wp-content\/uploads\/2024\/11\/1.png","_links":{"self":[{"href":"https:\/\/pakhams.com\/wp-json\/wp\/v2\/media\/36","targetHints":{"allow":["GET"]}}],"collection":[{"href":"https:\/\/pakhams.com\/wp-json\/wp\/v2\/media"}],"about":[{"href":"https:\/\/pakhams.com\/wp-json\/wp\/v2\/types\/attachment"}],"author":[{"embeddable":true,"href":"https:\/\/pakhams.com\/wp-json\/wp\/v2\/users\/1"}],"replies":[{"embeddable":true,"href":"https:\/\/pakhams.com\/wp-json\/wp\/v2\/comments?post=36"}],"wp:attached-to":[{"embeddable":true,"post_type":"page","id":35,"href":"https:\/\/pakhams.com\/wp-json\/wp\/v2\/pages\/35"}],"curies":[{"name":"wp","href":"https:\/\/api.w.org\/{rel}","templated":true}]}}]